pybacktrack/__init__.py
pybacktrack/age_to_depth.py
pybacktrack/age_to_depth_cli.py
pybacktrack/backstrip.py
pybacktrack/backstrip_cli.py
pybacktrack/backtrack.py
pybacktrack/backtrack_cli.py
pybacktrack/bundle_data.py
pybacktrack/dynamic_topography.py
pybacktrack/install_examples.py
pybacktrack/install_supplementary.py
pybacktrack/lithology.py
pybacktrack/paleo_bathymetry.py
pybacktrack/paleo_bathymetry_cli.py
pybacktrack/rifting.py
pybacktrack/sea_level.py
pybacktrack/version.py
pybacktrack/well.py
pybacktrack/bundle_data/age/Readme.txt
pybacktrack/bundle_data/age/agegrid_6m.nc
pybacktrack/bundle_data/crustal_thickness/Readme.txt
pybacktrack/bundle_data/crustal_thickness/crsthk.grd
pybacktrack/bundle_data/crustal_thickness/crsthk.xyz.zip
pybacktrack/bundle_data/dynamic_topography/Readme.txt
pybacktrack/bundle_data/dynamic_topography/models/AY18.grids
pybacktrack/bundle_data/dynamic_topography/models/KM16.grids
pybacktrack/bundle_data/dynamic_topography/models/M1.grids
pybacktrack/bundle_data/dynamic_topography/models/M2.grids
pybacktrack/bundle_data/dynamic_topography/models/M3.grids
pybacktrack/bundle_data/dynamic_topography/models/M4.grids
pybacktrack/bundle_data/dynamic_topography/models/M5.grids
pybacktrack/bundle_data/dynamic_topography/models/M6.grids
pybacktrack/bundle_data/dynamic_topography/models/M7.grids
pybacktrack/bundle_data/dynamic_topography/models/ngrand.grids
pybacktrack/bundle_data/dynamic_topography/models/s20rts.grids
pybacktrack/bundle_data/dynamic_topography/models/smean.grids
pybacktrack/bundle_data/dynamic_topography/models/terra.grids
pybacktrack/bundle_data/dynamic_topography/models/Cao2019/AY18/0.00.nc
pybacktrack/bundle_data/dynamic_topography/models/Cao2019/AY18/108.00.nc
pybacktrack/bundle_data/dynamic_topography/models/Cao2019/AY18/118.00.nc
pybacktrack/bundle_data/dynamic_topography/models/Cao2019/AY18/128.00.nc
pybacktrack/bundle_data/dynamic_topography/models/Cao2019/AY18/138.00.nc
pybacktrack-1.4.0.dist-info/LICENSE
pybacktrack-1.4.0.dist-info/METADATA
pybacktrack-1.4.0.dist-info/WHEEL
pybacktrack-1.4.0.dist-info/top_level.txt
pybacktrack-1.4.0.dist-info/RECORD
