Metadata-Version: 2.1
Name: pybacktrack
Version: 1.4.0
Summary: A tool for reconstructing paleobathymetry on oceanic and continental crust.
Home-page: https://github.com/EarthByte/pyBacktrack
Author: John Cannon
Author-email: john.cannon@sydney.edu.au
License: GPL
Project-URL: Documentation, http://pybacktrack.readthedocs.io
Project-URL: Source, https://github.com/EarthByte/pyBacktrack
Keywords: bathymetry backtrack backstrip rift subsidence tectonic
Classifier: Intended Audience :: Developers
Classifier: Intended Audience :: Education
Classifier: Intended Audience :: Science/Research
Classifier: License :: OSI Approved :: GNU General Public License v2 (GPLv2)
Classifier: Operating System :: POSIX :: Linux
Classifier: Operating System :: MacOS :: MacOS X
Classifier: Operating System :: Microsoft :: Windows
Classifier: Programming Language :: Python :: 2.7
Classifier: Programming Language :: Python :: 3
Classifier: Topic :: Scientific/Engineering
Requires-Python: >=2.7
License-File: LICENSE
Requires-Dist: numpy
Requires-Dist: scipy
